odoo/addons/project_wbs_task/README.rst
odoo/addons/project_wbs_task/__init__.py
odoo/addons/project_wbs_task/__manifest__.py
odoo/addons/project_wbs_task/i18n/it.po
odoo/addons/project_wbs_task/i18n/project_wbs_task.pot
odoo/addons/project_wbs_task/i18n/sl.po
odoo/addons/project_wbs_task/model/__init__.py
odoo/addons/project_wbs_task/model/project_task.py
odoo/addons/project_wbs_task/readme/CONTRIBUTORS.rst
odoo/addons/project_wbs_task/readme/DESCRIPTION.rst
odoo/addons/project_wbs_task/readme/USAGE.rst
odoo/addons/project_wbs_task/static/description/icon.png
odoo/addons/project_wbs_task/static/description/index.html
odoo/addons/project_wbs_task/tests/__init__.py
odoo/addons/project_wbs_task/tests/test_project_wbs_task.py
odoo/addons/project_wbs_task/view/project_task_view.xml
odoo/addons/project_wbs_task/view/project_view.xml
odoo12_addon_project_wbs_task-12.0.1.0.1.dist-info/METADATA
odoo12_addon_project_wbs_task-12.0.1.0.1.dist-info/WHEEL
odoo12_addon_project_wbs_task-12.0.1.0.1.dist-info/top_level.txt
odoo12_addon_project_wbs_task-12.0.1.0.1.dist-info/RECORD
